gmaild/__init__.py
gmaild/auth.py
gmaild/courier.py
gmaild/dispatch.py
gmaild/message.py
gmaild-0.0.12.dist-info/LICENSE
gmaild-0.0.12.dist-info/METADATA
gmaild-0.0.12.dist-info/WHEEL
gmaild-0.0.12.dist-info/top_level.txt
gmaild-0.0.12.dist-info/RECORD
