Metadata-Version: 2.1
Name: gmaild
Version: 0.0.12
Summary: Gmail Daemon
Home-page: UNKNOWN
Author: Parker Duckworth
License: Proprietary
Platform: UNKNOWN
Requires-Python: >=3.6
Requires-Dist: google-api-python-client
Requires-Dist: google-auth-httplib2
Requires-Dist: google-auth-oauthlib
Requires-Dist: schedule
